blaster/__init__.py
blaster/_config.py
blaster/config.py
blaster/connection_pool.py
blaster/constants.py
blaster/env.py
blaster/logging.py
blaster/mongo_orm.py
blaster/schema.py
blaster/server.py
blaster/cloud/__init__.py
blaster/cloud/analytics.py
blaster/cloud/push_tasks.py
blaster/cloud/run_later.py
blaster/cloud/storage.py
blaster/cloud/aws/__init__.py
blaster/cloud/aws/ses_utils.py
blaster/tools/__init__.py
blaster/tools/sanitize_html.py
blaster/utils/__init__.py
blaster/utils/data_utils.py
blaster/utils/events.py
blaster/utils/fork.py
blaster/utils/lat_long_utils.py
blaster/utils/phone_number_utils.py
blaster/utils/xss_html.py
blaster/utils/data/countries.json
blaster/utils/data/mime_types.json
blaster/websocket/__init__.py
blaster/websocket/_abnf.py
blaster/websocket/_app.py
blaster/websocket/_core.py
blaster/websocket/_exceptions.py
blaster/websocket/_handshake.py
blaster/websocket/_http.py
blaster/websocket/_logging.py
blaster/websocket/_socket.py
blaster/websocket/_ssl_compat.py
blaster/websocket/_url.py
blaster/websocket/_utils.py
blaster/websocket/server.py
blaster/websocket/tests/__init__.py
blaster/websocket/tests/test_websocket.py
examples/__init__.py
examples/fast_api_test.py
examples/gevent_wsgi_test.py
examples/meinheld_flask.py
examples/mongo_ormexample.py
examples/simple_examples.py
examples/test_chat_room.py
examples/tornado_hello_world.py
examples/wheezy_hello.py
test/__init__.py
test/test_command_line_parser.py
test/test_mongo_orm.py
test/test_phone_number_utils.py
test/test_schema.py
test/test_server.py
test/test_socket.py
test/test_tools.py
test/test_utils.py
test/timeit_snippets.py
blaster_server-0.1.51.dist-info/LICENSE.txt
blaster_server-0.1.51.dist-info/METADATA
blaster_server-0.1.51.dist-info/WHEEL
blaster_server-0.1.51.dist-info/top_level.txt
blaster_server-0.1.51.dist-info/RECORD
