Metadata-Version: 2.2
Name: blaster-server
Version: 0.1.51
Summary: Gevent based python server built from scratch for maximum performance
Home-page: https://github.com/abhinavabcd/blaster
Download-URL: https://github.com/abhinavabcd/blaster/archive/v0.0337b.tar.gz
Author: Abhinav Reddy
Author-email: abhinavabcd@gmail.com
License: MIT
Keywords: server,superfast,Like FastApi or Flask but 10x faster
Classifier: Development Status :: 3 - Alpha
Classifier: Intended Audience :: Developers
Classifier: Topic :: Software Development :: Build Tools
Classifier: License :: OSI Approved :: MIT License
Classifier: Programming Language :: Python :: 3
Classifier: Programming Language :: Python :: 3.4
Classifier: Programming Language :: Python :: 3.5
Classifier: Programming Language :: Python :: 3.6
License-File: LICENSE.txt
Requires-Dist: wheel>=0.34.2
Requires-Dist: pytz>=2020.1
Requires-Dist: gevent>=22.9.1
Requires-Dist: greenlet>=3.0.0
Requires-Dist: pymongo>=3.12.0
Requires-Dist: ujson>=5.10.0
Requires-Dist: python-dateutil>=2.8.1
Requires-Dist: requests>=2.25.1
Requires-Dist: requests-toolbelt>=1.0.0
Requires-Dist: urllib3>=1.26.4
Requires-Dist: cityhash>=0.4.8
Requires-Dist: PyYAML>=6.0
Dynamic: author
Dynamic: author-email
Dynamic: classifier
Dynamic: download-url
Dynamic: home-page
Dynamic: keywords
Dynamic: license
Dynamic: requires-dist
Dynamic: summary
